email_activities/__init__.py
email_activities/mails.py
ibott_mail-1.0.7.dist-info/LICENSE
ibott_mail-1.0.7.dist-info/METADATA
ibott_mail-1.0.7.dist-info/WHEEL
ibott_mail-1.0.7.dist-info/top_level.txt
ibott_mail-1.0.7.dist-info/RECORD
