Metadata-Version: 2.1
Name: ibott-mail
Version: 1.0.7
Summary: This packages crates a simple way to work with, emails, send, read and download attachments
Home-page: https://github.com/ecrespo66/files_and_folders
Author: OnameDohe
Author-email: OnameDohe <enrique.crespo.debenito@gmail.com>
License: Apache License
Project-URL: Homepage, https://github.com/ecrespo66/files_and_folders
Project-URL: Bug Tracker, https://github.com/ecrespo66/files_and_folders/issues
Classifier: Programming Language :: Python :: 3
Classifier: License :: OSI Approved :: MIT License
Classifier: Operating System :: OS Independent
Requires-Python: >=3.6
License-File: LICENSE
Requires-Dist: hatchling
Requires-Dist: imap-tools (==0.16.1)
